gs_batch/__init__.py
gs_batch/gs_batch.py
gs_batch/assets/PDFA_def.ps
gs_batch/assets/srgb.icc
gs_batch_pdf-0.6.4.dist-info/METADATA
gs_batch_pdf-0.6.4.dist-info/WHEEL
gs_batch_pdf-0.6.4.dist-info/entry_points.txt
gs_batch_pdf-0.6.4.dist-info/licenses/LICENSE
gs_batch_pdf-0.6.4.dist-info/RECORD
