Metadata-Version: 2.4
Name: gs-batch-pdf
Version: 0.6.4
Summary: cli tool wrapper for manipulating multiple pdfs file in parallel using ghostscript (compressing, convert to pdfa, etc.)
Project-URL: Homepage, https://github.com/kompre/gs-batch
Project-URL: Issue, https://github.com/kompre/gs-batch/issues
Author-email: kompre <s.follador@gmail.com>
License-Expression: MIT
License-File: LICENSE
Classifier: License :: OSI Approved :: MIT License
Classifier: Operating System :: OS Independent
Requires-Python: >=3.12
Requires-Dist: click>=8.1.7
Requires-Dist: show-in-file-manager<2,>=1.1.5
Requires-Dist: tqdm<5,>=4.66.5
